lkfit/__init__.py
lkfit/gaussian_fit.py
lkfit/poly.py
lkfit/proc.py
lkfit/pulse_response.py
lkfit-0.5.0.dist-info/METADATA
lkfit-0.5.0.dist-info/WHEEL
lkfit-0.5.0.dist-info/top_level.txt
lkfit-0.5.0.dist-info/RECORD
