Metadata-Version: 2.4
Name: lkfit
Version: 0.5.0
Summary: A Python library for fitting.
Author: Lukas Kontenis
Author-email: dse.ssd@gmail.com
Classifier: Programming Language :: Python :: 3
Classifier: License :: OSI Approved :: MIT License
Classifier: Operating System :: OS Independent
Requires-Python: >=3.6
Requires-Dist: numpy>=2.0
Requires-Dist: matplotlib>=3.8.4
Requires-Dist: scipy>=1.13.0
Requires-Dist: lkcom>=0.7.0
Requires-Dist: lmfit
Requires-Dist: scikit-image>=0.23.1
Dynamic: author
Dynamic: author-email
Dynamic: classifier
Dynamic: description
Dynamic: description-content-type
Dynamic: requires-dist
Dynamic: requires-python
Dynamic: summary
